[
 {
  "id": "bd9117cd62f4ea5a",
  "title": "Amazon Pay Later Bill",
  "url": "https://www.amazon.in/Axio-Amazon_Pay_Later-Amazon-Later-Bill/dp/B0BWF9ZQMN/ref=zg_bs_g_jewelry_d_sccl_1/521-1911117-0055910",
  "image": "https://images-eu.ssl-images-amazon.com/images/I/41NxrwwnQcL._AC_UL300_SR300,200_.jpg",
  "source": "Amazon",
  "country": "IN",
  "price": "₹100.00",
  "currency": null,
  "query": "bestsellers",
  "trend_score": 100,
  "first_seen": "2026-07-13",
  "scraped_at": "2026-07-13"
 },
 {
  "id": "bd9117cd62f4ea5a",
  "title": "Amazon Pay Later Bill",
  "url": "https://www.amazon.in/Axio-Amazon_Pay_Later-Amazon-Later-Bill/dp/B0BWF9ZQMN/ref=zg_bs_g_jewelry_d_sccl_1/521-1911117-0055910",
  "image": "https://images-eu.ssl-images-amazon.com/images/I/41NxrwwnQcL._AC_UL300_SR300,200_.jpg",
  "source": "Amazon",
  "country": "IN",
  "price": "₹100.00",
  "currency": null,
  "query": "bestsellers",
  "trend_score": 97,
  "first_seen": "2026-07-13",
  "scraped_at": "2026-07-13"
 },
 {
  "id": "f62a87f5988387e0",
  "title": "Seeotwo 2 Pieces Resin Hairband Shark Tooth Style Non-Slip Black Wave Sports Yoga Headband Fashion Adjustable Wavy Hair Hoop",
  "url": "https://www.amazon.in/Seeotwo-Hairband-Non-Slip-Headband-Adjustable/dp/B0D7K4XBY1/ref=zg_bs_g_jewelry_d_sccl_2/521-1911117-0055910",
  "image": "https://images-eu.ssl-images-amazon.com/images/I/317Nn+tQnPL._AC_UL300_SR300,200_.jpg",
  "source": "Amazon",
  "country": "IN",
  "price": "₹274.00",
  "currency": null,
  "query": "bestsellers",
  "trend_score": 94,
  "first_seen": "2026-07-13",
  "scraped_at": "2026-07-13"
 },
 {
  "id": "f62a87f5988387e0",
  "title": "Seeotwo 2 Pieces Resin Hairband Shark Tooth Style Non-Slip Black Wave Sports Yoga Headband Fashion Adjustable Wavy Hair Hoop",
  "url": "https://www.amazon.in/Seeotwo-Hairband-Non-Slip-Headband-Adjustable/dp/B0D7K4XBY1/ref=zg_bs_g_jewelry_d_sccl_2/521-1911117-0055910",
  "image": "https://images-eu.ssl-images-amazon.com/images/I/317Nn+tQnPL._AC_UL300_SR300,200_.jpg",
  "source": "Amazon",
  "country": "IN",
  "price": "₹274.00",
  "currency": null,
  "query": "bestsellers",
  "trend_score": 91,
  "first_seen": "2026-07-13",
  "scraped_at": "2026-07-13"
 },
 {
  "id": "5cba8138763ab7e0",
  "title": "Shining Diva Fashion 5 Pcs Latest Stylish Heart Butterfly Pearl Necklace Jewellery Set for Women Pendant Necklace Gifts for G",
  "url": "https://www.amazon.in/Shining-Diva-Fashion-Butterfly-16476np/dp/B0DYVPP86H/ref=zg_bs_g_jewelry_d_sccl_3/521-1911117-0055910",
  "image": "https://images-eu.ssl-images-amazon.com/images/I/713ZDAwhQuL._AC_UL300_SR300,200_.jpg",
  "source": "Amazon",
  "country": "IN",
  "price": "₹299.00",
  "currency": null,
  "query": "bestsellers",
  "trend_score": 88,
  "first_seen": "2026-07-13",
  "scraped_at": "2026-07-13"
 },
 {
  "id": "5cba8138763ab7e0",
  "title": "Shining Diva Fashion 5 Pcs Latest Stylish Heart Butterfly Pearl Necklace Jewellery Set for Women Pendant Necklace Gifts for G",
  "url": "https://www.amazon.in/Shining-Diva-Fashion-Butterfly-16476np/dp/B0DYVPP86H/ref=zg_bs_g_jewelry_d_sccl_3/521-1911117-0055910",
  "image": "https://images-eu.ssl-images-amazon.com/images/I/713ZDAwhQuL._AC_UL300_SR300,200_.jpg",
  "source": "Amazon",
  "country": "IN",
  "price": "₹299.00",
  "currency": null,
  "query": "bestsellers",
  "trend_score": 85,
  "first_seen": "2026-07-13",
  "scraped_at": "2026-07-13"
 },
 {
  "id": "abceabdb20ee5045",
  "title": "Astrotalk Dhan Yog Bracelet |Attracts Wealth & Prosperity | Manifest Wealth with Citrine, Jade, Tiger Eye, Clear Quartz & Pyr",
  "url": "https://www.amazon.in/Astrotalk-Prosperity-Aventurine-Certificate-Authenticity/dp/B0DTTXM92H/ref=zg_bs_g_jewelry_d_sccl_4/521-1911117-0055910",
  "image": "https://images-eu.ssl-images-amazon.com/images/I/6121JnclWxL._AC_UL300_SR300,200_.jpg",
  "source": "Amazon",
  "country": "IN",
  "price": "₹693.00",
  "currency": null,
  "query": "bestsellers",
  "trend_score": 82,
  "first_seen": "2026-07-13",
  "scraped_at": "2026-07-13"
 },
 {
  "id": "abceabdb20ee5045",
  "title": "Astrotalk Dhan Yog Bracelet |Attracts Wealth & Prosperity | Manifest Wealth with Citrine, Jade, Tiger Eye, Clear Quartz & Pyr",
  "url": "https://www.amazon.in/Astrotalk-Prosperity-Aventurine-Certificate-Authenticity/dp/B0DTTXM92H/ref=zg_bs_g_jewelry_d_sccl_4/521-1911117-0055910",
  "image": "https://images-eu.ssl-images-amazon.com/images/I/6121JnclWxL._AC_UL300_SR300,200_.jpg",
  "source": "Amazon",
  "country": "IN",
  "price": "₹693.00",
  "currency": null,
  "query": "bestsellers",
  "trend_score": 79,
  "first_seen": "2026-07-13",
  "scraped_at": "2026-07-13"
 },
 {
  "id": "43953f875e93256c",
  "title": "Shining Diva Fashion 5 Pcs Combo Latest Stylish Infinity Butterfly Pearl Necklace Jewellery Set for Women Pendant Necklace Gi",
  "url": "https://www.amazon.in/Shining-Diva-Fashion-Butterfly-15911np/dp/B0D3DCP7JQ/ref=zg_bs_g_jewelry_d_sccl_5/521-1911117-0055910",
  "image": "https://images-eu.ssl-images-amazon.com/images/I/71R2QnSdv+L._AC_UL300_SR300,200_.jpg",
  "source": "Amazon",
  "country": "IN",
  "price": "₹299.00",
  "currency": null,
  "query": "bestsellers",
  "trend_score": 76,
  "first_seen": "2026-07-13",
  "scraped_at": "2026-07-13"
 },
 {
  "id": "43953f875e93256c",
  "title": "Shining Diva Fashion 5 Pcs Combo Latest Stylish Infinity Butterfly Pearl Necklace Jewellery Set for Women Pendant Necklace Gi",
  "url": "https://www.amazon.in/Shining-Diva-Fashion-Butterfly-15911np/dp/B0D3DCP7JQ/ref=zg_bs_g_jewelry_d_sccl_5/521-1911117-0055910",
  "image": "https://images-eu.ssl-images-amazon.com/images/I/71R2QnSdv+L._AC_UL300_SR300,200_.jpg",
  "source": "Amazon",
  "country": "IN",
  "price": "₹299.00",
  "currency": null,
  "query": "bestsellers",
  "trend_score": 73,
  "first_seen": "2026-07-13",
  "scraped_at": "2026-07-13"
 },
 {
  "id": "10483800fa047b38",
  "title": "YouBella Jewellery Bracelets for Women Stylish Rose Gold Plated Crystal Bracelet Bangle Jewellery for Girls and Women",
  "url": "https://www.amazon.in/YouBella-Plated-Bracelet-Golden-YBBN_91340A/dp/B071CMQ6N2/ref=zg_bs_g_jewelry_d_sccl_6/521-1911117-0055910",
  "image": "https://images-eu.ssl-images-amazon.com/images/I/71P8z0DrFRL._AC_UL300_SR300,200_.jpg",
  "source": "Amazon",
  "country": "IN",
  "price": "₹172.00",
  "currency": null,
  "query": "bestsellers",
  "trend_score": 70,
  "first_seen": "2026-07-13",
  "scraped_at": "2026-07-13"
 },
 {
  "id": "10483800fa047b38",
  "title": "YouBella Jewellery Bracelets for Women Stylish Rose Gold Plated Crystal Bracelet Bangle Jewellery for Girls and Women",
  "url": "https://www.amazon.in/YouBella-Plated-Bracelet-Golden-YBBN_91340A/dp/B071CMQ6N2/ref=zg_bs_g_jewelry_d_sccl_6/521-1911117-0055910",
  "image": "https://images-eu.ssl-images-amazon.com/images/I/71P8z0DrFRL._AC_UL300_SR300,200_.jpg",
  "source": "Amazon",
  "country": "IN",
  "price": "₹172.00",
  "currency": null,
  "query": "bestsellers",
  "trend_score": 67,
  "first_seen": "2026-07-13",
  "scraped_at": "2026-07-13"
 },
 {
  "id": "ba78a37c37efc8c0",
  "title": "Shining Diva Fashion Latest Stylish Birthday Sash and Crown - Pack of 2 Pcs | Birthday Queen Crown | Birthday Gifts for Best",
  "url": "https://www.amazon.in/Shining-Diva-Fashion-Decorations-14860hb/dp/B0C5VKPPZJ/ref=zg_bs_g_jewelry_d_sccl_7/521-1911117-0055910",
  "image": "https://images-eu.ssl-images-amazon.com/images/I/61I3kWwEcLL._AC_UL300_SR300,200_.jpg",
  "source": "Amazon",
  "country": "IN",
  "price": "₹298.00",
  "currency": null,
  "query": "bestsellers",
  "trend_score": 64,
  "first_seen": "2026-07-13",
  "scraped_at": "2026-07-13"
 },
 {
  "id": "ba78a37c37efc8c0",
  "title": "Shining Diva Fashion Latest Stylish Birthday Sash and Crown - Pack of 2 Pcs | Birthday Queen Crown | Birthday Gifts for Best",
  "url": "https://www.amazon.in/Shining-Diva-Fashion-Decorations-14860hb/dp/B0C5VKPPZJ/ref=zg_bs_g_jewelry_d_sccl_7/521-1911117-0055910",
  "image": "https://images-eu.ssl-images-amazon.com/images/I/61I3kWwEcLL._AC_UL300_SR300,200_.jpg",
  "source": "Amazon",
  "country": "IN",
  "price": "₹298.00",
  "currency": null,
  "query": "bestsellers",
  "trend_score": 61,
  "first_seen": "2026-07-13",
  "scraped_at": "2026-07-13"
 },
 {
  "id": "c16a3cc9a0d60c42",
  "title": "INTESHA® Anti Tarnish 18K Gold Plated Floral Tulip Bracelet for Women & Girls | Elegant Daily Wear Jewelry | Gift for Her | P",
  "url": "https://www.amazon.in/INTESHA%C2%AE-Tarnish-Bracelet-Elegant-Jewelry/dp/B0GVB6HJCK/ref=zg_bs_g_jewelry_d_sccl_8/521-1911117-0055910",
  "image": "https://images-eu.ssl-images-amazon.com/images/I/51qooNMeJUL._AC_UL300_SR300,200_.jpg",
  "source": "Amazon",
  "country": "IN",
  "price": "₹209.00",
  "currency": null,
  "query": "bestsellers",
  "trend_score": 58,
  "first_seen": "2026-07-13",
  "scraped_at": "2026-07-13"
 },
 {
  "id": "c16a3cc9a0d60c42",
  "title": "INTESHA® Anti Tarnish 18K Gold Plated Floral Tulip Bracelet for Women & Girls | Elegant Daily Wear Jewelry | Gift for Her | P",
  "url": "https://www.amazon.in/INTESHA%C2%AE-Tarnish-Bracelet-Elegant-Jewelry/dp/B0GVB6HJCK/ref=zg_bs_g_jewelry_d_sccl_8/521-1911117-0055910",
  "image": "https://images-eu.ssl-images-amazon.com/images/I/51qooNMeJUL._AC_UL300_SR300,200_.jpg",
  "source": "Amazon",
  "country": "IN",
  "price": "₹209.00",
  "currency": null,
  "query": "bestsellers",
  "trend_score": 55,
  "first_seen": "2026-07-13",
  "scraped_at": "2026-07-13"
 },
 {
  "id": "1f9530d6576580da",
  "title": "Fashion Frill Silver Chain For Men Stylish Stainless Steel Bar Pendant Necklace Silver Chain Pendant For Men Boys Love Gifts",
  "url": "https://www.amazon.in/Fashion-Frill-Stainless-Pendant-Jewellery/dp/B0CV3T1WBB/ref=zg_bs_g_jewelry_d_sccl_9/521-1911117-0055910",
  "image": "https://images-eu.ssl-images-amazon.com/images/I/313sr5mjCEL._AC_UL300_SR300,200_.jpg",
  "source": "Amazon",
  "country": "IN",
  "price": "₹219.00",
  "currency": null,
  "query": "bestsellers",
  "trend_score": 52,
  "first_seen": "2026-07-13",
  "scraped_at": "2026-07-13"
 },
 {
  "id": "1f9530d6576580da",
  "title": "Fashion Frill Silver Chain For Men Stylish Stainless Steel Bar Pendant Necklace Silver Chain Pendant For Men Boys Love Gifts",
  "url": "https://www.amazon.in/Fashion-Frill-Stainless-Pendant-Jewellery/dp/B0CV3T1WBB/ref=zg_bs_g_jewelry_d_sccl_9/521-1911117-0055910",
  "image": "https://images-eu.ssl-images-amazon.com/images/I/313sr5mjCEL._AC_UL300_SR300,200_.jpg",
  "source": "Amazon",
  "country": "IN",
  "price": "₹219.00",
  "currency": null,
  "query": "bestsellers",
  "trend_score": 49,
  "first_seen": "2026-07-13",
  "scraped_at": "2026-07-13"
 },
 {
  "id": "9aeaa3bca295f685",
  "title": "Fashion Frill Earrings For Women Floral Vintage Design Traditional Drop Jhumke For Women Girls Love Gifts 12 Pair of Earrings",
  "url": "https://www.amazon.in/Fashion-Frill-Earrings-Floral-Traditional/dp/B0CTQ25GDW/ref=zg_bs_g_jewelry_d_sccl_10/521-1911117-0055910",
  "image": "https://images-eu.ssl-images-amazon.com/images/I/61wwQYaEuBL._AC_UL300_SR300,200_.jpg",
  "source": "Amazon",
  "country": "IN",
  "price": "₹329.00",
  "currency": null,
  "query": "bestsellers",
  "trend_score": 46,
  "first_seen": "2026-07-13",
  "scraped_at": "2026-07-13"
 },
 {
  "id": "9aeaa3bca295f685",
  "title": "Fashion Frill Earrings For Women Floral Vintage Design Traditional Drop Jhumke For Women Girls Love Gifts 12 Pair of Earrings",
  "url": "https://www.amazon.in/Fashion-Frill-Earrings-Floral-Traditional/dp/B0CTQ25GDW/ref=zg_bs_g_jewelry_d_sccl_10/521-1911117-0055910",
  "image": "https://images-eu.ssl-images-amazon.com/images/I/61wwQYaEuBL._AC_UL300_SR300,200_.jpg",
  "source": "Amazon",
  "country": "IN",
  "price": "₹329.00",
  "currency": null,
  "query": "bestsellers",
  "trend_score": 43,
  "first_seen": "2026-07-13",
  "scraped_at": "2026-07-13"
 },
 {
  "id": "066f6b3dd4648898",
  "title": "Nilu's Collection Infinity Shape Cubic Zirconia Diamond Bracelet for Women Jewelry for Gift, Adjustable Charm Bracelet",
  "url": "https://www.amazon.in/Nilus-Collection-Infinity-Zirconia-Adjustable/dp/B0DFCKWRBM/ref=zg_bs_g_jewelry_d_sccl_11/521-1911117-0055910",
  "image": "https://images-eu.ssl-images-amazon.com/images/I/51FoiQVzWWL._AC_UL300_SR300,200_.jpg",
  "source": "Amazon",
  "country": "IN",
  "price": "₹285.00",
  "currency": null,
  "query": "bestsellers",
  "trend_score": 40,
  "first_seen": "2026-07-13",
  "scraped_at": "2026-07-13"
 },
 {
  "id": "066f6b3dd4648898",
  "title": "Nilu's Collection Infinity Shape Cubic Zirconia Diamond Bracelet for Women Jewelry for Gift, Adjustable Charm Bracelet",
  "url": "https://www.amazon.in/Nilus-Collection-Infinity-Zirconia-Adjustable/dp/B0DFCKWRBM/ref=zg_bs_g_jewelry_d_sccl_11/521-1911117-0055910",
  "image": "https://images-eu.ssl-images-amazon.com/images/I/51FoiQVzWWL._AC_UL300_SR300,200_.jpg",
  "source": "Amazon",
  "country": "IN",
  "price": "₹285.00",
  "currency": null,
  "query": "bestsellers",
  "trend_score": 37,
  "first_seen": "2026-07-13",
  "scraped_at": "2026-07-13"
 },
 {
  "id": "67d683d9306e1b08",
  "title": "Shining Diva Fashion 22pcs Latest Stylish Stackable Kunckle Rings Set for Women and Girls Butterfly Heart Boho Gold and Silve",
  "url": "https://www.amazon.in/Shining-Diva-Fashion-Stylish-Rings/dp/B0BX62B58N/ref=zg_bs_g_jewelry_d_sccl_12/521-1911117-0055910",
  "image": "https://images-eu.ssl-images-amazon.com/images/I/61dK8fy1dRL._AC_UL300_SR300,200_.jpg",
  "source": "Amazon",
  "country": "IN",
  "price": "₹199.00",
  "currency": null,
  "query": "bestsellers",
  "trend_score": 34,
  "first_seen": "2026-07-13",
  "scraped_at": "2026-07-13"
 },
 {
  "id": "67d683d9306e1b08",
  "title": "Shining Diva Fashion 22pcs Latest Stylish Stackable Kunckle Rings Set for Women and Girls Butterfly Heart Boho Gold and Silve",
  "url": "https://www.amazon.in/Shining-Diva-Fashion-Stylish-Rings/dp/B0BX62B58N/ref=zg_bs_g_jewelry_d_sccl_12/521-1911117-0055910",
  "image": "https://images-eu.ssl-images-amazon.com/images/I/61dK8fy1dRL._AC_UL300_SR300,200_.jpg",
  "source": "Amazon",
  "country": "IN",
  "price": "₹199.00",
  "currency": null,
  "query": "bestsellers",
  "trend_score": 31,
  "first_seen": "2026-07-13",
  "scraped_at": "2026-07-13"
 },
 {
  "id": "a557474879593e27",
  "title": "Shining Diva Fashion Latest Stylish Multilayer Gold Plated Bangle Bracelet for Women and Girls (rr14669b) Set of 6",
  "url": "https://www.amazon.in/Shining-Diva-Fashion-Multilayer-rr14669b/dp/B0C1N366XM/ref=zg_bs_g_jewelry_d_sccl_13/521-1911117-0055910",
  "image": "https://images-eu.ssl-images-amazon.com/images/I/71UCk9VMVrL._AC_UL300_SR300,200_.jpg",
  "source": "Amazon",
  "country": "IN",
  "price": "₹299.00",
  "currency": null,
  "query": "bestsellers",
  "trend_score": 28,
  "first_seen": "2026-07-13",
  "scraped_at": "2026-07-13"
 },
 {
  "id": "a557474879593e27",
  "title": "Shining Diva Fashion Latest Stylish Multilayer Gold Plated Bangle Bracelet for Women and Girls (rr14669b) Set of 6",
  "url": "https://www.amazon.in/Shining-Diva-Fashion-Multilayer-rr14669b/dp/B0C1N366XM/ref=zg_bs_g_jewelry_d_sccl_13/521-1911117-0055910",
  "image": "https://images-eu.ssl-images-amazon.com/images/I/71UCk9VMVrL._AC_UL300_SR300,200_.jpg",
  "source": "Amazon",
  "country": "IN",
  "price": "₹299.00",
  "currency": null,
  "query": "bestsellers",
  "trend_score": 25,
  "first_seen": "2026-07-13",
  "scraped_at": "2026-07-13"
 },
 {
  "id": "185898f60c7761e8",
  "title": "Handmade Meenakari Lac Bangles Elephant Design | Traditional Rajasthani Lac Chudi Set for Women & Girls | Ethnic Bridal",
  "url": "https://www.amazon.in/Handmade-Meenakari-Elephant-Traditional-Rajasthani/dp/B0GXV4R1BQ/ref=zg_bs_g_jewelry_d_sccl_14/521-1911117-0055910",
  "image": "https://images-eu.ssl-images-amazon.com/images/I/81ukjkbAfCL._AC_UL300_SR300,200_.jpg",
  "source": "Amazon",
  "country": "IN",
  "price": "₹279.00",
  "currency": null,
  "query": "bestsellers",
  "trend_score": 22,
  "first_seen": "2026-07-13",
  "scraped_at": "2026-07-13"
 },
 {
  "id": "185898f60c7761e8",
  "title": "Handmade Meenakari Lac Bangles Elephant Design | Traditional Rajasthani Lac Chudi Set for Women & Girls | Ethnic Bridal",
  "url": "https://www.amazon.in/Handmade-Meenakari-Elephant-Traditional-Rajasthani/dp/B0GXV4R1BQ/ref=zg_bs_g_jewelry_d_sccl_14/521-1911117-0055910",
  "image": "https://images-eu.ssl-images-amazon.com/images/I/81ukjkbAfCL._AC_UL300_SR300,200_.jpg",
  "source": "Amazon",
  "country": "IN",
  "price": "₹279.00",
  "currency": null,
  "query": "bestsellers",
  "trend_score": 19,
  "first_seen": "2026-07-13",
  "scraped_at": "2026-07-13"
 },
 {
  "id": "49892ba02b6171c3",
  "title": "Kaher Kashmiri Glass Bangle with gunghro Set for Women| Traditional, Fancy Glass Chudi Set for Festival, Wedding, and Party (",
  "url": "https://www.amazon.in/Kaher-Kashmiri-Traditional-Festival-Multicolor/dp/B0GX2DHMB9/ref=zg_bs_g_jewelry_d_sccl_15/521-1911117-0055910",
  "image": "https://images-eu.ssl-images-amazon.com/images/I/71zpgY1ru0L._AC_UL300_SR300,200_.jpg",
  "source": "Amazon",
  "country": "IN",
  "price": "₹389.00",
  "currency": null,
  "query": "bestsellers",
  "trend_score": 16,
  "first_seen": "2026-07-13",
  "scraped_at": "2026-07-13"
 },
 {
  "id": "49892ba02b6171c3",
  "title": "Kaher Kashmiri Glass Bangle with gunghro Set for Women| Traditional, Fancy Glass Chudi Set for Festival, Wedding, and Party (",
  "url": "https://www.amazon.in/Kaher-Kashmiri-Traditional-Festival-Multicolor/dp/B0GX2DHMB9/ref=zg_bs_g_jewelry_d_sccl_15/521-1911117-0055910",
  "image": "https://images-eu.ssl-images-amazon.com/images/I/71zpgY1ru0L._AC_UL300_SR300,200_.jpg",
  "source": "Amazon",
  "country": "IN",
  "price": "₹389.00",
  "currency": null,
  "query": "bestsellers",
  "trend_score": 13,
  "first_seen": "2026-07-13",
  "scraped_at": "2026-07-13"
 },
 {
  "id": "5940613240e21be0",
  "title": "Non Tarnish Gold Chunky Rings for Women, 14K Gold Plated Statement Dome Rings Stacking Silver, Adjustable Mens Eternity Weddi",
  "url": "https://www.amazon.com/Stainless-Statement-Adjustable-Wedding-Jewelry/dp/B0DHH3JTQS/ref=zg_bs_g_7454939011_d_sccl_1/131-0200549-4909437",
  "image": "https://images-na.ssl-images-amazon.com/images/I/516MS0Wns5L._AC_UL300_SR300,200_.jpg",
  "source": "Amazon",
  "country": "US",
  "price": "$8.99",
  "currency": null,
  "query": "bestsellers",
  "trend_score": 100,
  "first_seen": "2026-07-13",
  "scraped_at": "2026-07-13"
 },
 {
  "id": "5940613240e21be0",
  "title": "Non Tarnish Gold Chunky Rings for Women, 14K Gold Plated Statement Dome Rings Stacking Silver, Adjustable Mens Eternity Weddi",
  "url": "https://www.amazon.com/Stainless-Statement-Adjustable-Wedding-Jewelry/dp/B0DHH3JTQS/ref=zg_bs_g_7454939011_d_sccl_1/131-0200549-4909437",
  "image": "https://images-na.ssl-images-amazon.com/images/I/516MS0Wns5L._AC_UL300_SR300,200_.jpg",
  "source": "Amazon",
  "country": "US",
  "price": "$8.99",
  "currency": null,
  "query": "bestsellers",
  "trend_score": 97,
  "first_seen": "2026-07-13",
  "scraped_at": "2026-07-13"
 },
 {
  "id": "8f6acfac3681928f",
  "title": "PAVOI Gold Plated Solid 925 Sterling Silver CZ Simulated Diamond Stackable Ring Eternity Bands for Women",
  "url": "https://www.amazon.com/PAVOI-Sterling-Stackable-Zirconia-Simulated/dp/B0F1N5P5W8/ref=zg_bs_g_7454939011_d_sccl_2/131-0200549-4909437",
  "image": "https://images-na.ssl-images-amazon.com/images/I/61-rraG8tIL._AC_UL300_SR300,200_.jpg",
  "source": "Amazon",
  "country": "US",
  "price": "$30.95",
  "currency": null,
  "query": "bestsellers",
  "trend_score": 94,
  "first_seen": "2026-07-13",
  "scraped_at": "2026-07-13"
 },
 {
  "id": "8f6acfac3681928f",
  "title": "PAVOI Gold Plated Solid 925 Sterling Silver CZ Simulated Diamond Stackable Ring Eternity Bands for Women",
  "url": "https://www.amazon.com/PAVOI-Sterling-Stackable-Zirconia-Simulated/dp/B0F1N5P5W8/ref=zg_bs_g_7454939011_d_sccl_2/131-0200549-4909437",
  "image": "https://images-na.ssl-images-amazon.com/images/I/61-rraG8tIL._AC_UL300_SR300,200_.jpg",
  "source": "Amazon",
  "country": "US",
  "price": "$30.95",
  "currency": null,
  "query": "bestsellers",
  "trend_score": 91,
  "first_seen": "2026-07-13",
  "scraped_at": "2026-07-13"
 },
 {
  "id": "d2559fad23ae0a9a",
  "title": "PAVOI 14K Gold Plated Eternity Ring for Women - Square-Cut Cubic Zirconia Rings - Stackable Love Wedding Band",
  "url": "https://www.amazon.com/PAVOI-White-Plated-Zirconia-Stackable/dp/B08CT77SB2/ref=zg_bs_g_7454939011_d_sccl_3/131-0200549-4909437",
  "image": "https://images-na.ssl-images-amazon.com/images/I/61peluWYLaL._AC_UL300_SR300,200_.jpg",
  "source": "Amazon",
  "country": "US",
  "price": "$14.95",
  "currency": null,
  "query": "bestsellers",
  "trend_score": 88,
  "first_seen": "2026-07-13",
  "scraped_at": "2026-07-13"
 },
 {
  "id": "d2559fad23ae0a9a",
  "title": "PAVOI 14K Gold Plated Eternity Ring for Women - Square-Cut Cubic Zirconia Rings - Stackable Love Wedding Band",
  "url": "https://www.amazon.com/PAVOI-White-Plated-Zirconia-Stackable/dp/B08CT77SB2/ref=zg_bs_g_7454939011_d_sccl_3/131-0200549-4909437",
  "image": "https://images-na.ssl-images-amazon.com/images/I/61peluWYLaL._AC_UL300_SR300,200_.jpg",
  "source": "Amazon",
  "country": "US",
  "price": "$14.95",
  "currency": null,
  "query": "bestsellers",
  "trend_score": 85,
  "first_seen": "2026-07-13",
  "scraped_at": "2026-07-13"
 },
 {
  "id": "2873c6a1adbbef28",
  "title": "iF YOU 25 Pcs Gold Stackable Ring Set for Women, Chunky Knuckle Finger Midi Rings, Silver Simple Stacking Cute Rings Pack Tre",
  "url": "https://www.amazon.com/iF-YOU-Knuckle-Stackable-Stacking/dp/B0DS2D78PT/ref=zg_bs_g_7454939011_d_sccl_4/131-0200549-4909437",
  "image": "https://images-na.ssl-images-amazon.com/images/I/816yEKPLG0L._AC_UL300_SR300,200_.jpg",
  "source": "Amazon",
  "country": "US",
  "price": "$6.29",
  "currency": null,
  "query": "bestsellers",
  "trend_score": 82,
  "first_seen": "2026-07-13",
  "scraped_at": "2026-07-13"
 },
 {
  "id": "2873c6a1adbbef28",
  "title": "iF YOU 25 Pcs Gold Stackable Ring Set for Women, Chunky Knuckle Finger Midi Rings, Silver Simple Stacking Cute Rings Pack Tre",
  "url": "https://www.amazon.com/iF-YOU-Knuckle-Stackable-Stacking/dp/B0DS2D78PT/ref=zg_bs_g_7454939011_d_sccl_4/131-0200549-4909437",
  "image": "https://images-na.ssl-images-amazon.com/images/I/816yEKPLG0L._AC_UL300_SR300,200_.jpg",
  "source": "Amazon",
  "country": "US",
  "price": "$6.29",
  "currency": null,
  "query": "bestsellers",
  "trend_score": 79,
  "first_seen": "2026-07-13",
  "scraped_at": "2026-07-13"
 },
 {
  "id": "4ca4a46e8a272f08",
  "title": "Dodder Gold Stackable Rings Set for Women, Gold Plated Chunky Crystal Finger Midi Stacking Rings, Dainty Statement Thumb Knuc",
  "url": "https://www.amazon.com/Dodder-Stackable-Stacking-Statement-Multiple/dp/B0GBW7CBVM/ref=zg_bs_g_7454939011_d_sccl_5/131-0200549-4909437",
  "image": "https://images-na.ssl-images-amazon.com/images/I/71xFGtw9OTL._AC_UL300_SR300,200_.jpg",
  "source": "Amazon",
  "country": "US",
  "price": "$7.97",
  "currency": null,
  "query": "bestsellers",
  "trend_score": 76,
  "first_seen": "2026-07-13",
  "scraped_at": "2026-07-13"
 },
 {
  "id": "4ca4a46e8a272f08",
  "title": "Dodder Gold Stackable Rings Set for Women, Gold Plated Chunky Crystal Finger Midi Stacking Rings, Dainty Statement Thumb Knuc",
  "url": "https://www.amazon.com/Dodder-Stackable-Stacking-Statement-Multiple/dp/B0GBW7CBVM/ref=zg_bs_g_7454939011_d_sccl_5/131-0200549-4909437",
  "image": "https://images-na.ssl-images-amazon.com/images/I/71xFGtw9OTL._AC_UL300_SR300,200_.jpg",
  "source": "Amazon",
  "country": "US",
  "price": "$7.97",
  "currency": null,
  "query": "bestsellers",
  "trend_score": 73,
  "first_seen": "2026-07-13",
  "scraped_at": "2026-07-13"
 },
 {
  "id": "4a6056072d9a68b1",
  "title": "Purplepig Stackable Rings for Women Non Tarnish, Two Tone Mixed Metal Dainty Eternity Band Set, 14K Gold & Sterling Silver Pl",
  "url": "https://www.amazon.com/Stackable-Minimalist-Zirconia-Hypoallergenic-Engagement/dp/B0GTPSL23T/ref=zg_bs_g_7454939011_d_sccl_6/131-0200549-4909437",
  "image": "https://images-na.ssl-images-amazon.com/images/I/61l78C+Ry0L._AC_UL300_SR300,200_.jpg",
  "source": "Amazon",
  "country": "US",
  "price": "$13.29",
  "currency": null,
  "query": "bestsellers",
  "trend_score": 70,
  "first_seen": "2026-07-13",
  "scraped_at": "2026-07-13"
 },
 {
  "id": "4a6056072d9a68b1",
  "title": "Purplepig Stackable Rings for Women Non Tarnish, Two Tone Mixed Metal Dainty Eternity Band Set, 14K Gold & Sterling Silver Pl",
  "url": "https://www.amazon.com/Stackable-Minimalist-Zirconia-Hypoallergenic-Engagement/dp/B0GTPSL23T/ref=zg_bs_g_7454939011_d_sccl_6/131-0200549-4909437",
  "image": "https://images-na.ssl-images-amazon.com/images/I/61l78C+Ry0L._AC_UL300_SR300,200_.jpg",
  "source": "Amazon",
  "country": "US",
  "price": "$13.29",
  "currency": null,
  "query": "bestsellers",
  "trend_score": 67,
  "first_seen": "2026-07-13",
  "scraped_at": "2026-07-13"
 },
 {
  "id": "bea130655857016c",
  "title": "PAVOI 14K Gold Plated Interlocked Stackable Rings for Women - Statement Mixed Metals Multi Ring Stack - Cubic Zirconia Connec",
  "url": "https://www.amazon.com/PAVOI-Plated-Stackable-Zirconia-Interlocking/dp/B0FDYVQ1ZP/ref=zg_bs_g_7454939011_d_sccl_7/131-0200549-4909437",
  "image": "https://images-na.ssl-images-amazon.com/images/I/71A2fjcEPhL._AC_UL300_SR300,200_.jpg",
  "source": "Amazon",
  "country": "US",
  "price": "$27.95",
  "currency": null,
  "query": "bestsellers",
  "trend_score": 64,
  "first_seen": "2026-07-13",
  "scraped_at": "2026-07-13"
 },
 {
  "id": "bea130655857016c",
  "title": "PAVOI 14K Gold Plated Interlocked Stackable Rings for Women - Statement Mixed Metals Multi Ring Stack - Cubic Zirconia Connec",
  "url": "https://www.amazon.com/PAVOI-Plated-Stackable-Zirconia-Interlocking/dp/B0FDYVQ1ZP/ref=zg_bs_g_7454939011_d_sccl_7/131-0200549-4909437",
  "image": "https://images-na.ssl-images-amazon.com/images/I/71A2fjcEPhL._AC_UL300_SR300,200_.jpg",
  "source": "Amazon",
  "country": "US",
  "price": "$27.95",
  "currency": null,
  "query": "bestsellers",
  "trend_score": 61,
  "first_seen": "2026-07-13",
  "scraped_at": "2026-07-13"
 },
 {
  "id": "a335cc0c16aaade4",
  "title": "KISS WIFE Gold Stackable Rings for Women, Dainty Knuckle Ring Set, Chunky Statement Thumb Midi Rings, Sparking Rhinestones Fi",
  "url": "https://www.amazon.com/KISS-WIFE-Stackable-Stacking-Sparkling/dp/B0CR45V6ZM/ref=zg_bs_g_7454939011_d_sccl_8/131-0200549-4909437",
  "image": "https://images-na.ssl-images-amazon.com/images/I/71MwcKOLYQL._AC_UL300_SR300,200_.jpg",
  "source": "Amazon",
  "country": "US",
  "price": "$9.97",
  "currency": null,
  "query": "bestsellers",
  "trend_score": 58,
  "first_seen": "2026-07-13",
  "scraped_at": "2026-07-13"
 },
 {
  "id": "a335cc0c16aaade4",
  "title": "KISS WIFE Gold Stackable Rings for Women, Dainty Knuckle Ring Set, Chunky Statement Thumb Midi Rings, Sparking Rhinestones Fi",
  "url": "https://www.amazon.com/KISS-WIFE-Stackable-Stacking-Sparkling/dp/B0CR45V6ZM/ref=zg_bs_g_7454939011_d_sccl_8/131-0200549-4909437",
  "image": "https://images-na.ssl-images-amazon.com/images/I/71MwcKOLYQL._AC_UL300_SR300,200_.jpg",
  "source": "Amazon",
  "country": "US",
  "price": "$9.97",
  "currency": null,
  "query": "bestsellers",
  "trend_score": 55,
  "first_seen": "2026-07-13",
  "scraped_at": "2026-07-13"
 },
 {
  "id": "81acda9f95a656e3",
  "title": "PAVOI Waterproof Link Ring - 14K Gold Plated Link Chain Ring for Women - Stackable Stainless Steel Thin Trendy Jewelry",
  "url": "https://www.amazon.com/PAVOI-Waterproof-Link-Ring-Stackable/dp/B0GDJ3G353/ref=zg_bs_g_7454939011_d_sccl_9/131-0200549-4909437",
  "image": "https://images-na.ssl-images-amazon.com/images/I/61ZQ+74xnQL._AC_UL300_SR300,200_.jpg",
  "source": "Amazon",
  "country": "US",
  "price": "$12.95",
  "currency": null,
  "query": "bestsellers",
  "trend_score": 52,
  "first_seen": "2026-07-13",
  "scraped_at": "2026-07-13"
 },
 {
  "id": "81acda9f95a656e3",
  "title": "PAVOI Waterproof Link Ring - 14K Gold Plated Link Chain Ring for Women - Stackable Stainless Steel Thin Trendy Jewelry",
  "url": "https://www.amazon.com/PAVOI-Waterproof-Link-Ring-Stackable/dp/B0GDJ3G353/ref=zg_bs_g_7454939011_d_sccl_9/131-0200549-4909437",
  "image": "https://images-na.ssl-images-amazon.com/images/I/61ZQ+74xnQL._AC_UL300_SR300,200_.jpg",
  "source": "Amazon",
  "country": "US",
  "price": "$12.95",
  "currency": null,
  "query": "bestsellers",
  "trend_score": 49,
  "first_seen": "2026-07-13",
  "scraped_at": "2026-07-13"
 },
 {
  "id": "e2962ed6fcb9ad92",
  "title": "NOKMIT 1mm 14K Gold Filled Rings for Women Girls Thin Gold Ring Dainty Cute Stacking Stackable Thumb Pinky Band Non Tarnish C",
  "url": "https://www.amazon.com/NOKMIT-Stackable-Knuckle-Stacking-Comfort/dp/B07Y6CBRQT/ref=zg_bs_g_7454939011_d_sccl_10/131-0200549-4909437",
  "image": "https://images-na.ssl-images-amazon.com/images/I/51KH0nyUmwL._AC_UL300_SR300,200_.jpg",
  "source": "Amazon",
  "country": "US",
  "price": "$6.49",
  "currency": null,
  "query": "bestsellers",
  "trend_score": 46,
  "first_seen": "2026-07-13",
  "scraped_at": "2026-07-13"
 },
 {
  "id": "e2962ed6fcb9ad92",
  "title": "NOKMIT 1mm 14K Gold Filled Rings for Women Girls Thin Gold Ring Dainty Cute Stacking Stackable Thumb Pinky Band Non Tarnish C",
  "url": "https://www.amazon.com/NOKMIT-Stackable-Knuckle-Stacking-Comfort/dp/B07Y6CBRQT/ref=zg_bs_g_7454939011_d_sccl_10/131-0200549-4909437",
  "image": "https://images-na.ssl-images-amazon.com/images/I/51KH0nyUmwL._AC_UL300_SR300,200_.jpg",
  "source": "Amazon",
  "country": "US",
  "price": "$6.49",
  "currency": null,
  "query": "bestsellers",
  "trend_score": 43,
  "first_seen": "2026-07-13",
  "scraped_at": "2026-07-13"
 },
 {
  "id": "f293f3d62162d7c9",
  "title": "LOLIAS 14K Gold Plated Stackable Rings for Women Non Tarnish - Dainty Cubic Zirconia Wedding Bands Ring Set Minimalist Trendy",
  "url": "https://www.amazon.com/LOLIAS-Plated-Stackable-Rings-Tarnish/dp/B0FHWJVYFN/ref=zg_bs_g_7454939011_d_sccl_11/131-0200549-4909437",
  "image": "https://images-na.ssl-images-amazon.com/images/I/61McRu6vSDL._AC_UL300_SR300,200_.jpg",
  "source": "Amazon",
  "country": "US",
  "price": "$12.99",
  "currency": null,
  "query": "bestsellers",
  "trend_score": 40,
  "first_seen": "2026-07-13",
  "scraped_at": "2026-07-13"
 },
 {
  "id": "f293f3d62162d7c9",
  "title": "LOLIAS 14K Gold Plated Stackable Rings for Women Non Tarnish - Dainty Cubic Zirconia Wedding Bands Ring Set Minimalist Trendy",
  "url": "https://www.amazon.com/LOLIAS-Plated-Stackable-Rings-Tarnish/dp/B0FHWJVYFN/ref=zg_bs_g_7454939011_d_sccl_11/131-0200549-4909437",
  "image": "https://images-na.ssl-images-amazon.com/images/I/61McRu6vSDL._AC_UL300_SR300,200_.jpg",
  "source": "Amazon",
  "country": "US",
  "price": "$12.99",
  "currency": null,
  "query": "bestsellers",
  "trend_score": 37,
  "first_seen": "2026-07-13",
  "scraped_at": "2026-07-13"
 },
 {
  "id": "9284b66232826bf4",
  "title": "QALO Stackable Rubber Engagement Rings for Women – Flexible Skin-Friendly Silicone Wedding Bands for Her – Lightweight All-Da",
  "url": "https://www.amazon.com/QALO-Stackable-Breathable-Engagement-Holographic/dp/B0CDHYMLW6/ref=zg_bs_g_7454939011_d_sccl_12/131-0200549-4909437",
  "image": "https://images-na.ssl-images-amazon.com/images/I/516bMtz-IvL._AC_UL300_SR300,200_.jpg",
  "source": "Amazon",
  "country": "US",
  "price": "$13.95",
  "currency": null,
  "query": "bestsellers",
  "trend_score": 34,
  "first_seen": "2026-07-13",
  "scraped_at": "2026-07-13"
 },
 {
  "id": "9284b66232826bf4",
  "title": "QALO Stackable Rubber Engagement Rings for Women – Flexible Skin-Friendly Silicone Wedding Bands for Her – Lightweight All-Da",
  "url": "https://www.amazon.com/QALO-Stackable-Breathable-Engagement-Holographic/dp/B0CDHYMLW6/ref=zg_bs_g_7454939011_d_sccl_12/131-0200549-4909437",
  "image": "https://images-na.ssl-images-amazon.com/images/I/516bMtz-IvL._AC_UL300_SR300,200_.jpg",
  "source": "Amazon",
  "country": "US",
  "price": "$13.95",
  "currency": null,
  "query": "bestsellers",
  "trend_score": 31,
  "first_seen": "2026-07-13",
  "scraped_at": "2026-07-13"
 },
 {
  "id": "3635cb5e72102987",
  "title": "THUNARAZ 14K Gold Plated Rings for Women Non Tarnish Stackable Chunky Rings Cubic Zirconia Thumb Ring Set Dainty Trendy State",
  "url": "https://www.amazon.com/THUNARAZ-Stackable-Zirconia-Statement-Engagement/dp/B0G3DZ7RZ2/ref=zg_bs_g_7454939011_d_sccl_13/131-0200549-4909437",
  "image": "https://images-na.ssl-images-amazon.com/images/I/61jvxTjuLLL._AC_UL300_SR300,200_.jpg",
  "source": "Amazon",
  "country": "US",
  "price": "$13.99",
  "currency": null,
  "query": "bestsellers",
  "trend_score": 28,
  "first_seen": "2026-07-13",
  "scraped_at": "2026-07-13"
 },
 {
  "id": "3635cb5e72102987",
  "title": "THUNARAZ 14K Gold Plated Rings for Women Non Tarnish Stackable Chunky Rings Cubic Zirconia Thumb Ring Set Dainty Trendy State",
  "url": "https://www.amazon.com/THUNARAZ-Stackable-Zirconia-Statement-Engagement/dp/B0G3DZ7RZ2/ref=zg_bs_g_7454939011_d_sccl_13/131-0200549-4909437",
  "image": "https://images-na.ssl-images-amazon.com/images/I/61jvxTjuLLL._AC_UL300_SR300,200_.jpg",
  "source": "Amazon",
  "country": "US",
  "price": "$13.99",
  "currency": null,
  "query": "bestsellers",
  "trend_score": 25,
  "first_seen": "2026-07-13",
  "scraped_at": "2026-07-13"
 },
 {
  "id": "82d8668cac2bae06",
  "title": "LevyPan 2-Pack 14K Gold Plated Stacking Rings for Oura Ring Gen 5/4/3, Cubic Zirconia Simulated oura ring accessories stack D",
  "url": "https://www.amazon.com/LevyPan-Stacking-Zirconia-Simulated-Diamond/dp/B0F1M92L97/ref=zg_bs_g_7454939011_d_sccl_14/131-0200549-4909437",
  "image": "https://images-na.ssl-images-amazon.com/images/I/51O1P2tVl5L._AC_UL300_SR300,200_.jpg",
  "source": "Amazon",
  "country": "US",
  "price": "$11.99",
  "currency": null,
  "query": "bestsellers",
  "trend_score": 22,
  "first_seen": "2026-07-13",
  "scraped_at": "2026-07-13"
 },
 {
  "id": "82d8668cac2bae06",
  "title": "LevyPan 2-Pack 14K Gold Plated Stacking Rings for Oura Ring Gen 5/4/3, Cubic Zirconia Simulated oura ring accessories stack D",
  "url": "https://www.amazon.com/LevyPan-Stacking-Zirconia-Simulated-Diamond/dp/B0F1M92L97/ref=zg_bs_g_7454939011_d_sccl_14/131-0200549-4909437",
  "image": "https://images-na.ssl-images-amazon.com/images/I/51O1P2tVl5L._AC_UL300_SR300,200_.jpg",
  "source": "Amazon",
  "country": "US",
  "price": "$11.99",
  "currency": null,
  "query": "bestsellers",
  "trend_score": 19,
  "first_seen": "2026-07-13",
  "scraped_at": "2026-07-13"
 },
 {
  "id": "6286b037dc7e2ff2",
  "title": "TOBENY Stackable Gold Rings for Women Non Tarnish Dainty 14K Gold Plated Stacking Cubic Zirconia Thumb Ring Set Trendy Statem",
  "url": "https://www.amazon.com/TOBENY-Stackable-Stacking-Statement-Engagement/dp/B0G1T3HSBQ/ref=zg_bs_g_7454939011_d_sccl_15/131-0200549-4909437",
  "image": "https://images-na.ssl-images-amazon.com/images/I/51FzqNK5ySL._AC_UL300_SR300,200_.jpg",
  "source": "Amazon",
  "country": "US",
  "price": "$13.98",
  "currency": null,
  "query": "bestsellers",
  "trend_score": 16,
  "first_seen": "2026-07-13",
  "scraped_at": "2026-07-13"
 },
 {
  "id": "6286b037dc7e2ff2",
  "title": "TOBENY Stackable Gold Rings for Women Non Tarnish Dainty 14K Gold Plated Stacking Cubic Zirconia Thumb Ring Set Trendy Statem",
  "url": "https://www.amazon.com/TOBENY-Stackable-Stacking-Statement-Engagement/dp/B0G1T3HSBQ/ref=zg_bs_g_7454939011_d_sccl_15/131-0200549-4909437",
  "image": "https://images-na.ssl-images-amazon.com/images/I/51FzqNK5ySL._AC_UL300_SR300,200_.jpg",
  "source": "Amazon",
  "country": "US",
  "price": "$13.98",
  "currency": null,
  "query": "bestsellers",
  "trend_score": 13,
  "first_seen": "2026-07-13",
  "scraped_at": "2026-07-13"
 },
 {
  "id": "0a4a3cc9f4b8ce6d",
  "title": "Nizoral® 2% Anti-Dandruff Shampoo, 100ml, Medical Treatment with Ketoconazole, Clinically Proven to Treat Dandruff, Flakes &",
  "url": "https://www.amazon.ae/Nizoral%C2%AE-Anti-Dandruff-Treatment-Ketoconazole-Clinically/dp/B0C6DQT3W3/ref=zg_bs_g_12149480031_d_sccl_1/259-1409795-6098934",
  "image": "https://images-eu.ssl-images-amazon.com/images/I/71WejvGF6YL._AC_UL300_SR300,200_.jpg",
  "source": "Amazon",
  "country": "AE",
  "price": "AED 36.00",
  "currency": null,
  "query": "bestsellers",
  "trend_score": 100,
  "first_seen": "2026-07-13",
  "scraped_at": "2026-07-13"
 },
 {
  "id": "0a4a3cc9f4b8ce6d",
  "title": "Nizoral® 2% Anti-Dandruff Shampoo, 100ml, Medical Treatment with Ketoconazole, Clinically Proven to Treat Dandruff, Flakes &",
  "url": "https://www.amazon.ae/Nizoral%C2%AE-Anti-Dandruff-Treatment-Ketoconazole-Clinically/dp/B0C6DQT3W3/ref=zg_bs_g_12149480031_d_sccl_1/259-1409795-6098934",
  "image": "https://images-eu.ssl-images-amazon.com/images/I/71WejvGF6YL._AC_UL300_SR300,200_.jpg",
  "source": "Amazon",
  "country": "AE",
  "price": "AED 36.00",
  "currency": null,
  "query": "bestsellers",
  "trend_score": 97,
  "first_seen": "2026-07-13",
  "scraped_at": "2026-07-13"
 },
 {
  "id": "ed30d76294c123e0",
  "title": "Garnier Hair Colour, With 3 Nourishing Oils, Grey Covereage, Long-lasting Shiny Colour, Natural-looking Result, For All Hair",
  "url": "https://www.amazon.ae/Garnier-Nourishing-Covereage-Long-lasting-Natural-looking/dp/B07MQP4SSS/ref=zg_bs_g_12149480031_d_sccl_2/259-1409795-6098934",
  "image": "https://images-eu.ssl-images-amazon.com/images/I/61FrXlNTa4L._AC_UL300_SR300,200_.jpg",
  "source": "Amazon",
  "country": "AE",
  "price": "AED 12.75",
  "currency": null,
  "query": "bestsellers",
  "trend_score": 94,
  "first_seen": "2026-07-13",
  "scraped_at": "2026-07-13"
 },
 {
  "id": "ed30d76294c123e0",
  "title": "Garnier Hair Colour, With 3 Nourishing Oils, Grey Covereage, Long-lasting Shiny Colour, Natural-looking Result, For All Hair",
  "url": "https://www.amazon.ae/Garnier-Nourishing-Covereage-Long-lasting-Natural-looking/dp/B07MQP4SSS/ref=zg_bs_g_12149480031_d_sccl_2/259-1409795-6098934",
  "image": "https://images-eu.ssl-images-amazon.com/images/I/61FrXlNTa4L._AC_UL300_SR300,200_.jpg",
  "source": "Amazon",
  "country": "AE",
  "price": "AED 12.75",
  "currency": null,
  "query": "bestsellers",
  "trend_score": 91,
  "first_seen": "2026-07-13",
  "scraped_at": "2026-07-13"
 },
 {
  "id": "e53c870cba133238",
  "title": "KOLESTON INTENSE SEMIKIT 303/0 DARK BROWN",
  "url": "https://www.amazon.ae/KOLESTON-INTENSE-SEMIKIT-DARK-BROWN/dp/B00PJZSEIQ/ref=zg_bs_g_12149480031_d_sccl_3/259-1409795-6098934",
  "image": "https://images-eu.ssl-images-amazon.com/images/I/81Hyq+5iBJL._AC_UL300_SR300,200_.jpg",
  "source": "Amazon",
  "country": "AE",
  "price": "AED 11.20",
  "currency": null,
  "query": "bestsellers",
  "trend_score": 88,
  "first_seen": "2026-07-13",
  "scraped_at": "2026-07-13"
 },
 {
  "id": "e53c870cba133238",
  "title": "KOLESTON INTENSE SEMIKIT 303/0 DARK BROWN",
  "url": "https://www.amazon.ae/KOLESTON-INTENSE-SEMIKIT-DARK-BROWN/dp/B00PJZSEIQ/ref=zg_bs_g_12149480031_d_sccl_3/259-1409795-6098934",
  "image": "https://images-eu.ssl-images-amazon.com/images/I/81Hyq+5iBJL._AC_UL300_SR300,200_.jpg",
  "source": "Amazon",
  "country": "AE",
  "price": "AED 11.20",
  "currency": null,
  "query": "bestsellers",
  "trend_score": 85,
  "first_seen": "2026-07-13",
  "scraped_at": "2026-07-13"
 },
 {
  "id": "475f7f5c3a568107",
  "title": "L'Oreal Paris Elvive Hyaluron Moisture Hydrating Shampoo 400ml + Conditioner 360ml for Frizzy & Dehydrated Hair",
  "url": "https://www.amazon.ae/LOreal-Paris-Hydrating-Conditioner-Dehydrated/dp/B0CP9S449F/ref=zg_bs_g_12149480031_d_sccl_4/259-1409795-6098934",
  "image": "https://images-eu.ssl-images-amazon.com/images/I/619wX3iUxGL._AC_UL300_SR300,200_.jpg",
  "source": "Amazon",
  "country": "AE",
  "price": "AED 34.25",
  "currency": null,
  "query": "bestsellers",
  "trend_score": 82,
  "first_seen": "2026-07-13",
  "scraped_at": "2026-07-13"
 },
 {
  "id": "475f7f5c3a568107",
  "title": "L'Oreal Paris Elvive Hyaluron Moisture Hydrating Shampoo 400ml + Conditioner 360ml for Frizzy & Dehydrated Hair",
  "url": "https://www.amazon.ae/LOreal-Paris-Hydrating-Conditioner-Dehydrated/dp/B0CP9S449F/ref=zg_bs_g_12149480031_d_sccl_4/259-1409795-6098934",
  "image": "https://images-eu.ssl-images-amazon.com/images/I/619wX3iUxGL._AC_UL300_SR300,200_.jpg",
  "source": "Amazon",
  "country": "AE",
  "price": "AED 34.25",
  "currency": null,
  "query": "bestsellers",
  "trend_score": 79,
  "first_seen": "2026-07-13",
  "scraped_at": "2026-07-13"
 },
 {
  "id": "d08c74179c068a74",
  "title": "Dove Bond Intense Repair, Treatment Hair Mask, for healthy, vital and smooth hair, BIO PROTEIN CARE, Repairs, nourishes signs",
  "url": "https://www.amazon.ae/Dove-Intense-Treatment-healthy-nourishes/dp/B0DNPYY1VM/ref=zg_bs_g_12149480031_d_sccl_5/259-1409795-6098934",
  "image": "https://images-eu.ssl-images-amazon.com/images/I/51ueEJGgAuL._AC_UL300_SR300,200_.jpg",
  "source": "Amazon",
  "country": "AE",
  "price": "AED 27.36",
  "currency": null,
  "query": "bestsellers",
  "trend_score": 76,
  "first_seen": "2026-07-13",
  "scraped_at": "2026-07-13"
 },
 {
  "id": "d08c74179c068a74",
  "title": "Dove Bond Intense Repair, Treatment Hair Mask, for healthy, vital and smooth hair, BIO PROTEIN CARE, Repairs, nourishes signs",
  "url": "https://www.amazon.ae/Dove-Intense-Treatment-healthy-nourishes/dp/B0DNPYY1VM/ref=zg_bs_g_12149480031_d_sccl_5/259-1409795-6098934",
  "image": "https://images-eu.ssl-images-amazon.com/images/I/51ueEJGgAuL._AC_UL300_SR300,200_.jpg",
  "source": "Amazon",
  "country": "AE",
  "price": "AED 27.36",
  "currency": null,
  "query": "bestsellers",
  "trend_score": 73,
  "first_seen": "2026-07-13",
  "scraped_at": "2026-07-13"
 },
 {
  "id": "b5afc5d4e7e6468a",
  "title": "Be Bodywise Rosemary Hair Growth Serum (Roll On)| Promotes Hair Growth, Stimulates Hair Follicles | 3% Rosemary, 3% Redensyl",
  "url": "https://www.amazon.ae/Be-Bodywise-Rosemary-Stimulates-Follicles/dp/B0CPJB7WW7/ref=zg_bs_g_12149480031_d_sccl_6/259-1409795-6098934",
  "image": "https://images-eu.ssl-images-amazon.com/images/I/61hPKEtnF2L._AC_UL300_SR300,200_.jpg",
  "source": "Amazon",
  "country": "AE",
  "price": "AED 43.10",
  "currency": null,
  "query": "bestsellers",
  "trend_score": 70,
  "first_seen": "2026-07-13",
  "scraped_at": "2026-07-13"
 },
 {
  "id": "b5afc5d4e7e6468a",
  "title": "Be Bodywise Rosemary Hair Growth Serum (Roll On)| Promotes Hair Growth, Stimulates Hair Follicles | 3% Rosemary, 3% Redensyl",
  "url": "https://www.amazon.ae/Be-Bodywise-Rosemary-Stimulates-Follicles/dp/B0CPJB7WW7/ref=zg_bs_g_12149480031_d_sccl_6/259-1409795-6098934",
  "image": "https://images-eu.ssl-images-amazon.com/images/I/61hPKEtnF2L._AC_UL300_SR300,200_.jpg",
  "source": "Amazon",
  "country": "AE",
  "price": "AED 43.10",
  "currency": null,
  "query": "bestsellers",
  "trend_score": 67,
  "first_seen": "2026-07-13",
  "scraped_at": "2026-07-13"
 },
 {
  "id": "325c7cdcb0fe8dbe",
  "title": "Bare Anatomy Anti-Dandruff Shampoo | Up To 100% Dandruff Reduction | ZPTO-Free | pH 5.3 | Salicylic Acid, Piroctone Olamine &",
  "url": "https://www.amazon.ae/Bare-Anatomy-Anti-Dandruff-Reduction-Non-Drying/dp/B0BJZXKH12/ref=zg_bs_g_12149480031_d_sccl_7/259-1409795-6098934",
  "image": "https://images-eu.ssl-images-amazon.com/images/I/41YLe0BPPuL._AC_UL300_SR300,200_.jpg",
  "source": "Amazon",
  "country": "AE",
  "price": "AED 33.99",
  "currency": null,
  "query": "bestsellers",
  "trend_score": 64,
  "first_seen": "2026-07-13",
  "scraped_at": "2026-07-13"
 },
 {
  "id": "325c7cdcb0fe8dbe",
  "title": "Bare Anatomy Anti-Dandruff Shampoo | Up To 100% Dandruff Reduction | ZPTO-Free | pH 5.3 | Salicylic Acid, Piroctone Olamine &",
  "url": "https://www.amazon.ae/Bare-Anatomy-Anti-Dandruff-Reduction-Non-Drying/dp/B0BJZXKH12/ref=zg_bs_g_12149480031_d_sccl_7/259-1409795-6098934",
  "image": "https://images-eu.ssl-images-amazon.com/images/I/41YLe0BPPuL._AC_UL300_SR300,200_.jpg",
  "source": "Amazon",
  "country": "AE",
  "price": "AED 33.99",
  "currency": null,
  "query": "bestsellers",
  "trend_score": 61,
  "first_seen": "2026-07-13",
  "scraped_at": "2026-07-13"
 },
 {
  "id": "bf72432126a0c102",
  "title": "Head & Shoulders Daily Clean Anti-Dandruff Shampoo, Deep Cleansing Formula for Fresh, Clean Hair & Scalp, Up to 100% Dandruff",
  "url": "https://www.amazon.ae/Head-Shoulders-Anti-Dandruff-Protection-Effectively/dp/B07FZP6L83/ref=zg_bs_g_12149480031_d_sccl_8/259-1409795-6098934",
  "image": "https://images-eu.ssl-images-amazon.com/images/I/71wBDryC5iL._AC_UL300_SR300,200_.jpg",
  "source": "Amazon",
  "country": "AE",
  "price": "AED 28.00",
  "currency": null,
  "query": "bestsellers",
  "trend_score": 58,
  "first_seen": "2026-07-13",
  "scraped_at": "2026-07-13"
 },
 {
  "id": "bf72432126a0c102",
  "title": "Head & Shoulders Daily Clean Anti-Dandruff Shampoo, Deep Cleansing Formula for Fresh, Clean Hair & Scalp, Up to 100% Dandruff",
  "url": "https://www.amazon.ae/Head-Shoulders-Anti-Dandruff-Protection-Effectively/dp/B07FZP6L83/ref=zg_bs_g_12149480031_d_sccl_8/259-1409795-6098934",
  "image": "https://images-eu.ssl-images-amazon.com/images/I/71wBDryC5iL._AC_UL300_SR300,200_.jpg",
  "source": "Amazon",
  "country": "AE",
  "price": "AED 28.00",
  "currency": null,
  "query": "bestsellers",
  "trend_score": 55,
  "first_seen": "2026-07-13",
  "scraped_at": "2026-07-13"
 },
 {
  "id": "d08194c632ffff8b",
  "title": "Botanic Hearth 100% Pure Rosemary Oil For Hair Growth | 198 ML | Infused With Biotin, Jojoba & castor Oil | Hair strengthenin",
  "url": "https://www.amazon.ae/Botanic-Hearth-strengthening-Nourishing-Volumizing/dp/B0C6XJMSGP/ref=zg_bs_g_12149480031_d_sccl_9/259-1409795-6098934",
  "image": "https://images-eu.ssl-images-amazon.com/images/I/516wde97ffL._AC_UL300_SR300,200_.jpg",
  "source": "Amazon",
  "country": "AE",
  "price": "AED 38.00",
  "currency": null,
  "query": "bestsellers",
  "trend_score": 52,
  "first_seen": "2026-07-13",
  "scraped_at": "2026-07-13"
 },
 {
  "id": "d08194c632ffff8b",
  "title": "Botanic Hearth 100% Pure Rosemary Oil For Hair Growth | 198 ML | Infused With Biotin, Jojoba & castor Oil | Hair strengthenin",
  "url": "https://www.amazon.ae/Botanic-Hearth-strengthening-Nourishing-Volumizing/dp/B0C6XJMSGP/ref=zg_bs_g_12149480031_d_sccl_9/259-1409795-6098934",
  "image": "https://images-eu.ssl-images-amazon.com/images/I/516wde97ffL._AC_UL300_SR300,200_.jpg",
  "source": "Amazon",
  "country": "AE",
  "price": "AED 38.00",
  "currency": null,
  "query": "bestsellers",
  "trend_score": 49,
  "first_seen": "2026-07-13",
  "scraped_at": "2026-07-13"
 },
 {
  "id": "26d5b0ae030f9da5",
  "title": "Pantene Pro-V Smooth & Silky Shampoo with Anti-Frizz Formula for Dry & Frizzy Hair, Deep Nourishment & Thicker Stronger Hair",
  "url": "https://www.amazon.ae/Pantene-Shampoo-Anti-Frizz-Nourishment-Stronger/dp/B07MTX7HL2/ref=zg_bs_g_12149480031_d_sccl_10/259-1409795-6098934",
  "image": "https://images-eu.ssl-images-amazon.com/images/I/61y82yd4akL._AC_UL300_SR300,200_.jpg",
  "source": "Amazon",
  "country": "AE",
  "price": "AED 24.00",
  "currency": null,
  "query": "bestsellers",
  "trend_score": 46,
  "first_seen": "2026-07-13",
  "scraped_at": "2026-07-13"
 },
 {
  "id": "26d5b0ae030f9da5",
  "title": "Pantene Pro-V Smooth & Silky Shampoo with Anti-Frizz Formula for Dry & Frizzy Hair, Deep Nourishment & Thicker Stronger Hair",
  "url": "https://www.amazon.ae/Pantene-Shampoo-Anti-Frizz-Nourishment-Stronger/dp/B07MTX7HL2/ref=zg_bs_g_12149480031_d_sccl_10/259-1409795-6098934",
  "image": "https://images-eu.ssl-images-amazon.com/images/I/61y82yd4akL._AC_UL300_SR300,200_.jpg",
  "source": "Amazon",
  "country": "AE",
  "price": "AED 24.00",
  "currency": null,
  "query": "bestsellers",
  "trend_score": 43,
  "first_seen": "2026-07-13",
  "scraped_at": "2026-07-13"
 },
 {
  "id": "ccd1e5c37b3b8f4d",
  "title": "L’Oréal Paris L'Oreal Elnett Satin Hair Spray Super Hold 75ml",
  "url": "https://www.amazon.ae/LOr%C3%A9al-Paris-LOreal-Elnett-Satin/dp/B00UO7I9OS/ref=zg_bs_g_12149480031_d_sccl_11/259-1409795-6098934",
  "image": "https://images-eu.ssl-images-amazon.com/images/I/41CwyGO47tL._AC_UL300_SR300,200_.jpg",
  "source": "Amazon",
  "country": "AE",
  "price": "AED 10.50",
  "currency": null,
  "query": "bestsellers",
  "trend_score": 40,
  "first_seen": "2026-07-13",
  "scraped_at": "2026-07-13"
 },
 {
  "id": "ccd1e5c37b3b8f4d",
  "title": "L’Oréal Paris L'Oreal Elnett Satin Hair Spray Super Hold 75ml",
  "url": "https://www.amazon.ae/LOr%C3%A9al-Paris-LOreal-Elnett-Satin/dp/B00UO7I9OS/ref=zg_bs_g_12149480031_d_sccl_11/259-1409795-6098934",
  "image": "https://images-eu.ssl-images-amazon.com/images/I/41CwyGO47tL._AC_UL300_SR300,200_.jpg",
  "source": "Amazon",
  "country": "AE",
  "price": "AED 10.50",
  "currency": null,
  "query": "bestsellers",
  "trend_score": 37,
  "first_seen": "2026-07-13",
  "scraped_at": "2026-07-13"
 },
 {
  "id": "6ff08d6b882a73a3",
  "title": "Herbal Essences Bio Renew, Argan Oil of Morocco, Shampoo 400ml + Conditioner 400ml",
  "url": "https://www.amazon.ae/Herbal-Essences-Morocco-Shampoo-Conditioner/dp/B07FZNHMTZ/ref=zg_bs_g_12149480031_d_sccl_12/259-1409795-6098934",
  "image": "https://images-eu.ssl-images-amazon.com/images/I/71orwlV8XQL._AC_UL300_SR300,200_.jpg",
  "source": "Amazon",
  "country": "AE",
  "price": "AED 19.00",
  "currency": null,
  "query": "bestsellers",
  "trend_score": 34,
  "first_seen": "2026-07-13",
  "scraped_at": "2026-07-13"
 },
 {
  "id": "6ff08d6b882a73a3",
  "title": "Herbal Essences Bio Renew, Argan Oil of Morocco, Shampoo 400ml + Conditioner 400ml",
  "url": "https://www.amazon.ae/Herbal-Essences-Morocco-Shampoo-Conditioner/dp/B07FZNHMTZ/ref=zg_bs_g_12149480031_d_sccl_12/259-1409795-6098934",
  "image": "https://images-eu.ssl-images-amazon.com/images/I/71orwlV8XQL._AC_UL300_SR300,200_.jpg",
  "source": "Amazon",
  "country": "AE",
  "price": "AED 19.00",
  "currency": null,
  "query": "bestsellers",
  "trend_score": 31,
  "first_seen": "2026-07-13",
  "scraped_at": "2026-07-13"
 },
 {
  "id": "824e5bfe29a8b9af",
  "title": "L’Oréal Paris L'OREAL Elvive Hyaluron Pure Shampoo For Oily Scalp & Dehydrated Lengths -200ml",
  "url": "https://www.amazon.ae/Paris-Hyaluron-Shampoo-Dehydrated-Lengths/dp/B0D41W847J/ref=zg_bs_g_12149480031_d_sccl_13/259-1409795-6098934",
  "image": "https://images-eu.ssl-images-amazon.com/images/I/6108sQF4GjL._AC_UL300_SR300,200_.jpg",
  "source": "Amazon",
  "country": "AE",
  "price": "AED 8.80",
  "currency": null,
  "query": "bestsellers",
  "trend_score": 28,
  "first_seen": "2026-07-13",
  "scraped_at": "2026-07-13"
 },
 {
  "id": "824e5bfe29a8b9af",
  "title": "L’Oréal Paris L'OREAL Elvive Hyaluron Pure Shampoo For Oily Scalp & Dehydrated Lengths -200ml",
  "url": "https://www.amazon.ae/Paris-Hyaluron-Shampoo-Dehydrated-Lengths/dp/B0D41W847J/ref=zg_bs_g_12149480031_d_sccl_13/259-1409795-6098934",
  "image": "https://images-eu.ssl-images-amazon.com/images/I/6108sQF4GjL._AC_UL300_SR300,200_.jpg",
  "source": "Amazon",
  "country": "AE",
  "price": "AED 8.80",
  "currency": null,
  "query": "bestsellers",
  "trend_score": 25,
  "first_seen": "2026-07-13",
  "scraped_at": "2026-07-13"
 },
 {
  "id": "edb96d39a3b4a402",
  "title": "Herbal Essences Bio:Renew, Coconut Milk, Shampoo 400ml + Conditioner 400ml",
  "url": "https://www.amazon.ae/Herbal-Essences-Bio-Coconut-Conditioner/dp/B07FZNVQLN/ref=zg_bs_g_12149480031_d_sccl_14/259-1409795-6098934",
  "image": "https://images-eu.ssl-images-amazon.com/images/I/81LT2EE612L._AC_UL300_SR300,200_.jpg",
  "source": "Amazon",
  "country": "AE",
  "price": "AED 19.00",
  "currency": null,
  "query": "bestsellers",
  "trend_score": 22,
  "first_seen": "2026-07-13",
  "scraped_at": "2026-07-13"
 },
 {
  "id": "edb96d39a3b4a402",
  "title": "Herbal Essences Bio:Renew, Coconut Milk, Shampoo 400ml + Conditioner 400ml",
  "url": "https://www.amazon.ae/Herbal-Essences-Bio-Coconut-Conditioner/dp/B07FZNVQLN/ref=zg_bs_g_12149480031_d_sccl_14/259-1409795-6098934",
  "image": "https://images-eu.ssl-images-amazon.com/images/I/81LT2EE612L._AC_UL300_SR300,200_.jpg",
  "source": "Amazon",
  "country": "AE",
  "price": "AED 19.00",
  "currency": null,
  "query": "bestsellers",
  "trend_score": 19,
  "first_seen": "2026-07-13",
  "scraped_at": "2026-07-13"
 },
 {
  "id": "c659139dc780f6ac",
  "title": "L’Oréal Paris Casting Crème Gloss 300 Dark Brown",
  "url": "https://www.amazon.ae/LOr%C3%A9al-Paris-Casting-Cr%C3%A8me-Gloss/dp/B003KXJF14/ref=zg_bs_g_12149480031_d_sccl_15/259-1409795-6098934",
  "image": "https://images-eu.ssl-images-amazon.com/images/I/61qJGx52mNL._AC_UL300_SR300,200_.jpg",
  "source": "Amazon",
  "country": "AE",
  "price": "AED 38.00",
  "currency": null,
  "query": "bestsellers",
  "trend_score": 16,
  "first_seen": "2026-07-13",
  "scraped_at": "2026-07-13"
 },
 {
  "id": "c659139dc780f6ac",
  "title": "L’Oréal Paris Casting Crème Gloss 300 Dark Brown",
  "url": "https://www.amazon.ae/LOr%C3%A9al-Paris-Casting-Cr%C3%A8me-Gloss/dp/B003KXJF14/ref=zg_bs_g_12149480031_d_sccl_15/259-1409795-6098934",
  "image": "https://images-eu.ssl-images-amazon.com/images/I/61qJGx52mNL._AC_UL300_SR300,200_.jpg",
  "source": "Amazon",
  "country": "AE",
  "price": "AED 38.00",
  "currency": null,
  "query": "bestsellers",
  "trend_score": 13,
  "first_seen": "2026-07-13",
  "scraped_at": "2026-07-13"
 },
 {
  "id": "e0e43900c63539fe",
  "title": "ULTECHNOVO Digital Hanging Luggage Scale Portable Handheld Baggage Scale for Travel Suitcase Scale for Traveling with LCD Dis",
  "url": "https://www.amazon.sa/-/en/ULTECHNOVO-Portable-Handheld-Suitcase-Traveling/dp/B07XCM3X1F/ref=zg_bs_g_fashion_d_sccl_1/262-6813618-2868150",
  "image": "https://images-eu.ssl-images-amazon.com/images/I/61nqZJR7BoL._AC_UL300_SR300,200_.jpg",
  "source": "Amazon",
  "country": "SA",
  "price": "SAR 15.00",
  "currency": null,
  "query": "bestsellers",
  "trend_score": 100,
  "first_seen": "2026-07-13",
  "scraped_at": "2026-07-13"
 },
 {
  "id": "e0e43900c63539fe",
  "title": "ULTECHNOVO Digital Hanging Luggage Scale Portable Handheld Baggage Scale for Travel Suitcase Scale for Traveling with LCD Dis",
  "url": "https://www.amazon.sa/-/en/ULTECHNOVO-Portable-Handheld-Suitcase-Traveling/dp/B07XCM3X1F/ref=zg_bs_g_fashion_d_sccl_1/262-6813618-2868150",
  "image": "https://images-eu.ssl-images-amazon.com/images/I/61nqZJR7BoL._AC_UL300_SR300,200_.jpg",
  "source": "Amazon",
  "country": "SA",
  "price": "SAR 15.00",
  "currency": null,
  "query": "bestsellers",
  "trend_score": 97,
  "first_seen": "2026-07-13",
  "scraped_at": "2026-07-13"
 },
 {
  "id": "f7749ad4577029bf",
  "title": "SKY-TOUCH 6Pcs SET Travel Luggage Organizer Packing Cubes Set Storage Bag Waterproof Laundry Bag Traveling Accessories - Grey",
  "url": "https://www.amazon.sa/-/en/SKY-TOUCH-Organizer-Waterproof-Traveling-Accessories/dp/B09KQ54PSD/ref=zg_bs_g_fashion_d_sccl_2/262-6813618-2868150",
  "image": "https://images-eu.ssl-images-amazon.com/images/I/71Sfyew8NAL._AC_UL300_SR300,200_.jpg",
  "source": "Amazon",
  "country": "SA",
  "price": "SAR 21.90",
  "currency": null,
  "query": "bestsellers",
  "trend_score": 94,
  "first_seen": "2026-07-13",
  "scraped_at": "2026-07-13"
 },
 {
  "id": "f7749ad4577029bf",
  "title": "SKY-TOUCH 6Pcs SET Travel Luggage Organizer Packing Cubes Set Storage Bag Waterproof Laundry Bag Traveling Accessories - Grey",
  "url": "https://www.amazon.sa/-/en/SKY-TOUCH-Organizer-Waterproof-Traveling-Accessories/dp/B09KQ54PSD/ref=zg_bs_g_fashion_d_sccl_2/262-6813618-2868150",
  "image": "https://images-eu.ssl-images-amazon.com/images/I/71Sfyew8NAL._AC_UL300_SR300,200_.jpg",
  "source": "Amazon",
  "country": "SA",
  "price": "SAR 21.90",
  "currency": null,
  "query": "bestsellers",
  "trend_score": 91,
  "first_seen": "2026-07-13",
  "scraped_at": "2026-07-13"
 },
 {
  "id": "84412dd3b99f1442",
  "title": "infino 5 Pairs Men's 100% Cotton Crew Socks: Mid-Calf, Dress Socks, Moisture Wicking, Suitable for All Seasons, Striped Patte",
  "url": "https://www.amazon.sa/-/en/infinoTM-5-Pair-100-Cotton-Socks/dp/B0CR7CPJDV/ref=zg_bs_g_fashion_d_sccl_3/262-6813618-2868150",
  "image": "https://images-eu.ssl-images-amazon.com/images/I/71pimxGI-jL._AC_UL300_SR300,200_.jpg",
  "source": "Amazon",
  "country": "SA",
  "price": "SAR 37.79",
  "currency": null,
  "query": "bestsellers",
  "trend_score": 88,
  "first_seen": "2026-07-13",
  "scraped_at": "2026-07-13"
 },
 {
  "id": "84412dd3b99f1442",
  "title": "infino 5 Pairs Men's 100% Cotton Crew Socks: Mid-Calf, Dress Socks, Moisture Wicking, Suitable for All Seasons, Striped Patte",
  "url": "https://www.amazon.sa/-/en/infinoTM-5-Pair-100-Cotton-Socks/dp/B0CR7CPJDV/ref=zg_bs_g_fashion_d_sccl_3/262-6813618-2868150",
  "image": "https://images-eu.ssl-images-amazon.com/images/I/71pimxGI-jL._AC_UL300_SR300,200_.jpg",
  "source": "Amazon",
  "country": "SA",
  "price": "SAR 37.79",
  "currency": null,
  "query": "bestsellers",
  "trend_score": 85,
  "first_seen": "2026-07-13",
  "scraped_at": "2026-07-13"
 },
 {
  "id": "3072528c6b11da27",
  "title": "Skechers SUMMITS womens SPORTS",
  "url": "https://www.amazon.sa/-/en/SKECHERS-WOMEN-SUMMITS-BLACK-40/dp/B0DVZQ28HC/ref=zg_bs_g_fashion_d_sccl_4/262-6813618-2868150",
  "image": "https://images-eu.ssl-images-amazon.com/images/I/71JNacJY+qL._AC_UL300_SR300,200_.jpg",
  "source": "Amazon",
  "country": "SA",
  "price": "SAR 102.75",
  "currency": null,
  "query": "bestsellers",
  "trend_score": 82,
  "first_seen": "2026-07-13",
  "scraped_at": "2026-07-13"
 },
 {
  "id": "3072528c6b11da27",
  "title": "Skechers SUMMITS womens SPORTS",
  "url": "https://www.amazon.sa/-/en/SKECHERS-WOMEN-SUMMITS-BLACK-40/dp/B0DVZQ28HC/ref=zg_bs_g_fashion_d_sccl_4/262-6813618-2868150",
  "image": "https://images-eu.ssl-images-amazon.com/images/I/71JNacJY+qL._AC_UL300_SR300,200_.jpg",
  "source": "Amazon",
  "country": "SA",
  "price": "SAR 102.75",
  "currency": null,
  "query": "bestsellers",
  "trend_score": 79,
  "first_seen": "2026-07-13",
  "scraped_at": "2026-07-13"
 },
 {
  "id": "692d331997b4826b",
  "title": "GoodTool Shower Slippers, Bath Slippers, Lightweight Non-Slip House Slippers for Women and Men - Quick-Dry Indoor and Bathroo",
  "url": "https://www.amazon.sa/-/en/GoodTool-Shower-Slippers-Lightweight-Non-Slip/dp/B0G2QWJ6JB/ref=zg_bs_g_fashion_d_sccl_5/262-6813618-2868150",
  "image": "https://images-eu.ssl-images-amazon.com/images/I/71iERUpsm7L._AC_UL300_SR300,200_.jpg",
  "source": "Amazon",
  "country": "SA",
  "price": "SAR 13.50",
  "currency": null,
  "query": "bestsellers",
  "trend_score": 76,
  "first_seen": "2026-07-13",
  "scraped_at": "2026-07-13"
 },
 {
  "id": "692d331997b4826b",
  "title": "GoodTool Shower Slippers, Bath Slippers, Lightweight Non-Slip House Slippers for Women and Men - Quick-Dry Indoor and Bathroo",
  "url": "https://www.amazon.sa/-/en/GoodTool-Shower-Slippers-Lightweight-Non-Slip/dp/B0G2QWJ6JB/ref=zg_bs_g_fashion_d_sccl_5/262-6813618-2868150",
  "image": "https://images-eu.ssl-images-amazon.com/images/I/71iERUpsm7L._AC_UL300_SR300,200_.jpg",
  "source": "Amazon",
  "country": "SA",
  "price": "SAR 13.50",
  "currency": null,
  "query": "bestsellers",
  "trend_score": 73,
  "first_seen": "2026-07-13",
  "scraped_at": "2026-07-13"
 },
 {
  "id": "ae55a65f8f8bd6b7",
  "title": "SKY-TOUCH 12 Pieces Waterproof Shoe Storage Bags, Non-Woven Fabric with Drawstring and Transparent Window for Travel, Gym and",
  "url": "https://www.amazon.sa/-/en/SKY-TOUCH-Shoe-Storage-Transparent-Bag/dp/B0BW636KF8/ref=zg_bs_g_fashion_d_sccl_6/262-6813618-2868150",
  "image": "https://images-eu.ssl-images-amazon.com/images/I/61J4ezyHZQL._AC_UL300_SR300,200_.jpg",
  "source": "Amazon",
  "country": "SA",
  "price": "SAR 20.90",
  "currency": null,
  "query": "bestsellers",
  "trend_score": 70,
  "first_seen": "2026-07-13",
  "scraped_at": "2026-07-13"
 },
 {
  "id": "ae55a65f8f8bd6b7",
  "title": "SKY-TOUCH 12 Pieces Waterproof Shoe Storage Bags, Non-Woven Fabric with Drawstring and Transparent Window for Travel, Gym and",
  "url": "https://www.amazon.sa/-/en/SKY-TOUCH-Shoe-Storage-Transparent-Bag/dp/B0BW636KF8/ref=zg_bs_g_fashion_d_sccl_6/262-6813618-2868150",
  "image": "https://images-eu.ssl-images-amazon.com/images/I/61J4ezyHZQL._AC_UL300_SR300,200_.jpg",
  "source": "Amazon",
  "country": "SA",
  "price": "SAR 20.90",
  "currency": null,
  "query": "bestsellers",
  "trend_score": 67,
  "first_seen": "2026-07-13",
  "scraped_at": "2026-07-13"
 },
 {
  "id": "4ed3eca6ca714c93",
  "title": "GoodTool Women's Long Sun Protection Gloves, Summer UV Driving Gloves, Touchscreen Ice-Silk Sunblock Gloves for Cycling and O",
  "url": "https://www.amazon.sa/-/en/GoodTool-Protection-Touchscreen-Ice-Silk-Activities/dp/B0FTS84F3L/ref=zg_bs_g_fashion_d_sccl_7/262-6813618-2868150",
  "image": "https://images-eu.ssl-images-amazon.com/images/I/718WVobF2RL._AC_UL300_SR300,200_.jpg",
  "source": "Amazon",
  "country": "SA",
  "price": "SAR 15.22",
  "currency": null,
  "query": "bestsellers",
  "trend_score": 64,
  "first_seen": "2026-07-13",
  "scraped_at": "2026-07-13"
 },
 {
  "id": "4ed3eca6ca714c93",
  "title": "GoodTool Women's Long Sun Protection Gloves, Summer UV Driving Gloves, Touchscreen Ice-Silk Sunblock Gloves for Cycling and O",
  "url": "https://www.amazon.sa/-/en/GoodTool-Protection-Touchscreen-Ice-Silk-Activities/dp/B0FTS84F3L/ref=zg_bs_g_fashion_d_sccl_7/262-6813618-2868150",
  "image": "https://images-eu.ssl-images-amazon.com/images/I/718WVobF2RL._AC_UL300_SR300,200_.jpg",
  "source": "Amazon",
  "country": "SA",
  "price": "SAR 15.22",
  "currency": null,
  "query": "bestsellers",
  "trend_score": 61,
  "first_seen": "2026-07-13",
  "scraped_at": "2026-07-13"
 },
 {
  "id": "8c365e6d5b14a67e",
  "title": "Women's Nightgown - Lace Trim Side Slit Modal Sleep Dress, Soft Loungewear & Sleepwear for Women",
  "url": "https://www.amazon.sa/-/en/Womens-Nightgown-Modal-Loungewear-Sleepwear/dp/B0GVYJFZNB/ref=zg_bs_g_fashion_d_sccl_8/262-6813618-2868150",
  "image": "https://images-eu.ssl-images-amazon.com/images/I/61kd6LCOjWL._AC_UL300_SR300,200_.jpg",
  "source": "Amazon",
  "country": "SA",
  "price": "SAR 9.89",
  "currency": null,
  "query": "bestsellers",
  "trend_score": 58,
  "first_seen": "2026-07-13",
  "scraped_at": "2026-07-13"
 },
 {
  "id": "8c365e6d5b14a67e",
  "title": "Women's Nightgown - Lace Trim Side Slit Modal Sleep Dress, Soft Loungewear & Sleepwear for Women",
  "url": "https://www.amazon.sa/-/en/Womens-Nightgown-Modal-Loungewear-Sleepwear/dp/B0GVYJFZNB/ref=zg_bs_g_fashion_d_sccl_8/262-6813618-2868150",
  "image": "https://images-eu.ssl-images-amazon.com/images/I/61kd6LCOjWL._AC_UL300_SR300,200_.jpg",
  "source": "Amazon",
  "country": "SA",
  "price": "SAR 9.89",
  "currency": null,
  "query": "bestsellers",
  "trend_score": 55,
  "first_seen": "2026-07-13",
  "scraped_at": "2026-07-13"
 },
 {
  "id": "be121a51173fb9cc",
  "title": "Calvin Klein Mens Medium Rise Trunk Boxer Shorts(Pack of 3) (pack of 3)",
  "url": "https://www.amazon.sa/-/en/Calvin-Klein-Medium-Trunk-Shorts/dp/B001BEAWZM/ref=zg_bs_g_fashion_d_sccl_9/262-6813618-2868150",
  "image": "https://images-eu.ssl-images-amazon.com/images/I/51XLO0xdwmL._AC_UL300_SR300,200_.jpg",
  "source": "Amazon",
  "country": "SA",
  "price": "SAR 221.83",
  "currency": null,
  "query": "bestsellers",
  "trend_score": 52,
  "first_seen": "2026-07-13",
  "scraped_at": "2026-07-13"
 },
 {
  "id": "be121a51173fb9cc",
  "title": "Calvin Klein Mens Medium Rise Trunk Boxer Shorts(Pack of 3) (pack of 3)",
  "url": "https://www.amazon.sa/-/en/Calvin-Klein-Medium-Trunk-Shorts/dp/B001BEAWZM/ref=zg_bs_g_fashion_d_sccl_9/262-6813618-2868150",
  "image": "https://images-eu.ssl-images-amazon.com/images/I/51XLO0xdwmL._AC_UL300_SR300,200_.jpg",
  "source": "Amazon",
  "country": "SA",
  "price": "SAR 221.83",
  "currency": null,
  "query": "bestsellers",
  "trend_score": 49,
  "first_seen": "2026-07-13",
  "scraped_at": "2026-07-13"
 },
 {
  "id": "c681964bd69f098e",
  "title": "adidas Galaxy 7 Running Shoes mens Non-Football Low Shoes",
  "url": "https://www.amazon.sa/-/en/Adidas-GALAXY-Mens-core-black/dp/B0CKXT75DR/ref=zg_bs_g_fashion_d_sccl_10/262-6813618-2868150",
  "image": "https://images-eu.ssl-images-amazon.com/images/I/51FUMTitvML._AC_UL300_SR300,200_.jpg",
  "source": "Amazon",
  "country": "SA",
  "price": "SAR 135.00",
  "currency": null,
  "query": "bestsellers",
  "trend_score": 46,
  "first_seen": "2026-07-13",
  "scraped_at": "2026-07-13"
 },
 {
  "id": "c681964bd69f098e",
  "title": "adidas Galaxy 7 Running Shoes mens Non-Football Low Shoes",
  "url": "https://www.amazon.sa/-/en/Adidas-GALAXY-Mens-core-black/dp/B0CKXT75DR/ref=zg_bs_g_fashion_d_sccl_10/262-6813618-2868150",
  "image": "https://images-eu.ssl-images-amazon.com/images/I/51FUMTitvML._AC_UL300_SR300,200_.jpg",
  "source": "Amazon",
  "country": "SA",
  "price": "SAR 135.00",
  "currency": null,
  "query": "bestsellers",
  "trend_score": 43,
  "first_seen": "2026-07-13",
  "scraped_at": "2026-07-13"
 },
 {
  "id": "3c2877d74b9e0963",
  "title": "UimoKi Muslim Women Swimsuit Rash Guard Set Modest Islamic Full Coverage Long Sleeve Top and Pants Swim Cap Surf Wetsuit Beac",
  "url": "https://www.amazon.sa/-/en/UimoKi-Swimsuit-Islamic-Coverage-Beachwear/dp/B0GK5P6BRP/ref=zg_bs_g_fashion_d_sccl_11/262-6813618-2868150",
  "image": "https://images-eu.ssl-images-amazon.com/images/I/51oK8lmfMVL._AC_UL300_SR300,200_.jpg",
  "source": "Amazon",
  "country": "SA",
  "price": "SAR 89.99",
  "currency": null,
  "query": "bestsellers",
  "trend_score": 40,
  "first_seen": "2026-07-13",
  "scraped_at": "2026-07-13"
 },
 {
  "id": "3c2877d74b9e0963",
  "title": "UimoKi Muslim Women Swimsuit Rash Guard Set Modest Islamic Full Coverage Long Sleeve Top and Pants Swim Cap Surf Wetsuit Beac",
  "url": "https://www.amazon.sa/-/en/UimoKi-Swimsuit-Islamic-Coverage-Beachwear/dp/B0GK5P6BRP/ref=zg_bs_g_fashion_d_sccl_11/262-6813618-2868150",
  "image": "https://images-eu.ssl-images-amazon.com/images/I/51oK8lmfMVL._AC_UL300_SR300,200_.jpg",
  "source": "Amazon",
  "country": "SA",
  "price": "SAR 89.99",
  "currency": null,
  "query": "bestsellers",
  "trend_score": 37,
  "first_seen": "2026-07-13",
  "scraped_at": "2026-07-13"
 },
 {
  "id": "fc6f3558aa24b2f4",
  "title": "SKY-TOUCH Digital Luggage Scale, Portable Luggage Weight Scale, Hanging Suitcase Weigher for Travel, Suitcase Scale with Temp",
  "url": "https://www.amazon.sa/-/en/SKY-TOUCH-Portable-Suitcase-Temperature-Measurement/dp/B0D2DN769W/ref=zg_bs_g_fashion_d_sccl_12/262-6813618-2868150",
  "image": "https://images-eu.ssl-images-amazon.com/images/I/51ydJ1PVSCL._AC_UL300_SR300,200_.jpg",
  "source": "Amazon",
  "country": "SA",
  "price": "SAR 15.00",
  "currency": null,
  "query": "bestsellers",
  "trend_score": 34,
  "first_seen": "2026-07-13",
  "scraped_at": "2026-07-13"
 },
 {
  "id": "fc6f3558aa24b2f4",
  "title": "SKY-TOUCH Digital Luggage Scale, Portable Luggage Weight Scale, Hanging Suitcase Weigher for Travel, Suitcase Scale with Temp",
  "url": "https://www.amazon.sa/-/en/SKY-TOUCH-Portable-Suitcase-Temperature-Measurement/dp/B0D2DN769W/ref=zg_bs_g_fashion_d_sccl_12/262-6813618-2868150",
  "image": "https://images-eu.ssl-images-amazon.com/images/I/51ydJ1PVSCL._AC_UL300_SR300,200_.jpg",
  "source": "Amazon",
  "country": "SA",
  "price": "SAR 15.00",
  "currency": null,
  "query": "bestsellers",
  "trend_score": 31,
  "first_seen": "2026-07-13",
  "scraped_at": "2026-07-13"
 },
 {
  "id": "d2d950ebf37afd17",
  "title": "infino Men's 5-Pack Boxer Briefs - Mid-Rise, Anti-Chafing Stretch Cotton, Breathable Athletic Underwear in Assorted Colors (B",
  "url": "https://www.amazon.sa/-/en/infino%C2%AE-Mens-5-Pack-Boxer-Briefs/dp/B0CS9Q3RYG/ref=zg_bs_g_fashion_d_sccl_13/262-6813618-2868150",
  "image": "https://images-eu.ssl-images-amazon.com/images/I/610YeWqKDAL._AC_UL300_SR300,200_.jpg",
  "source": "Amazon",
  "country": "SA",
  "price": "SAR 59.49",
  "currency": null,
  "query": "bestsellers",
  "trend_score": 28,
  "first_seen": "2026-07-13",
  "scraped_at": "2026-07-13"
 },
 {
  "id": "d2d950ebf37afd17",
  "title": "infino Men's 5-Pack Boxer Briefs - Mid-Rise, Anti-Chafing Stretch Cotton, Breathable Athletic Underwear in Assorted Colors (B",
  "url": "https://www.amazon.sa/-/en/infino%C2%AE-Mens-5-Pack-Boxer-Briefs/dp/B0CS9Q3RYG/ref=zg_bs_g_fashion_d_sccl_13/262-6813618-2868150",
  "image": "https://images-eu.ssl-images-amazon.com/images/I/610YeWqKDAL._AC_UL300_SR300,200_.jpg",
  "source": "Amazon",
  "country": "SA",
  "price": "SAR 59.49",
  "currency": null,
  "query": "bestsellers",
  "trend_score": 25,
  "first_seen": "2026-07-13",
  "scraped_at": "2026-07-13"
 },
 {
  "id": "5d172aa08c679f69",
  "title": "infino™ Men's Cotton Socks - Lined, Moisture Wicking, Odor Proof, Athletic Ankle Socks for Men, 3 Pack Classic Colors (Black,",
  "url": "https://www.amazon.sa/-/en/infino%C2%AE-Performance-Athletic-Socks-5-Pack/dp/B0DHS6PW23/ref=zg_bs_g_fashion_d_sccl_14/262-6813618-2868150",
  "image": "https://images-eu.ssl-images-amazon.com/images/I/71dT1tetnQL._AC_UL300_SR300,200_.jpg",
  "source": "Amazon",
  "country": "SA",
  "price": "SAR 35.09",
  "currency": null,
  "query": "bestsellers",
  "trend_score": 22,
  "first_seen": "2026-07-13",
  "scraped_at": "2026-07-13"
 },
 {
  "id": "5d172aa08c679f69",
  "title": "infino™ Men's Cotton Socks - Lined, Moisture Wicking, Odor Proof, Athletic Ankle Socks for Men, 3 Pack Classic Colors (Black,",
  "url": "https://www.amazon.sa/-/en/infino%C2%AE-Performance-Athletic-Socks-5-Pack/dp/B0DHS6PW23/ref=zg_bs_g_fashion_d_sccl_14/262-6813618-2868150",
  "image": "https://images-eu.ssl-images-amazon.com/images/I/71dT1tetnQL._AC_UL300_SR300,200_.jpg",
  "source": "Amazon",
  "country": "SA",
  "price": "SAR 35.09",
  "currency": null,
  "query": "bestsellers",
  "trend_score": 19,
  "first_seen": "2026-07-13",
  "scraped_at": "2026-07-13"
 },
 {
  "id": "c202fbbd46eda1f4",
  "title": "CARFIA Retro Polarized Sunglasses For Men UV400 Protection Chunky Square 90s Style Trendy Classic Glass",
  "url": "https://www.amazon.sa/-/en/Polarized-Sunglasses-Protection-Driving-Fishing/dp/B07JKG6W9P/ref=zg_bs_g_fashion_d_sccl_15/262-6813618-2868150",
  "image": "https://images-eu.ssl-images-amazon.com/images/I/61VQmsCfVeL._AC_UL300_SR300,200_.jpg",
  "source": "Amazon",
  "country": "SA",
  "price": "SAR 110.46",
  "currency": null,
  "query": "bestsellers",
  "trend_score": 16,
  "first_seen": "2026-07-13",
  "scraped_at": "2026-07-13"
 },
 {
  "id": "c202fbbd46eda1f4",
  "title": "CARFIA Retro Polarized Sunglasses For Men UV400 Protection Chunky Square 90s Style Trendy Classic Glass",
  "url": "https://www.amazon.sa/-/en/Polarized-Sunglasses-Protection-Driving-Fishing/dp/B07JKG6W9P/ref=zg_bs_g_fashion_d_sccl_15/262-6813618-2868150",
  "image": "https://images-eu.ssl-images-amazon.com/images/I/61VQmsCfVeL._AC_UL300_SR300,200_.jpg",
  "source": "Amazon",
  "country": "SA",
  "price": "SAR 110.46",
  "currency": null,
  "query": "bestsellers",
  "trend_score": 13,
  "first_seen": "2026-07-13",
  "scraped_at": "2026-07-13"
 }
]